{
"Perfect Anatomy": "(deformed:1.4), (mutated:1.3), extra limbs, (missing fingers:1.4), bad proportions, disfigured",
  "Symmetrical Face": "(asymmetrical:1.3), wandering eye, crooked nose, distorted facial features, uneven",
  "Detailed Extremities": "(fused fingers:1.4), (blurry hands:1.3), extra toes, missing limbs, bad anatomy",
  "Stable Pose": "(clipping:1.3), (floating:1.3), unstable posture, falling, sliding, impossible physics",
  "Hyper-Realistic Skin Texture": "(smooth:1.3), plastic, (airbrushed:1.3), flat skin, doll-like, no pores",
  "Natural Skin Imperfections": "perfect skin, (retouched:1.3), flawless, airbrushed, makeup, plastic",
  "Ocular Realism / Catchlights": "dead eyes, (dull eyes:1.3), no reflections, matte iris, blind eyes",
  "Subsurface Scattering (Skin)": "opaque, (solid skin:1.3), lifeless, cold, grey skin, clay-like",
  "Micro-Expression Wrinkles": "(smooth forehead:1.3), botox, no lines, plastic, young, airbrushed",
  "Unpolished Realism": "(perfect:1.3), airbrushed, studio quality, symmetrical, retouched",
  "Physics-Based Weight Distribution": "no compression, (stiff:1.2), floating, no weight, hard, static",
  "Grounded Surface Contact": "floating, (hovering:1.3), no contact shadows, clipping through floor",
  "Fabric Dynamics": "stiff clothes, (no wrinkles:1.3), flat fabric, frozen cloth, plastic",
  "Environmental Interaction": "static, (dry:1.2), no wind effect, clean, isolated, no reaction",
  "Muscular Tension / Definition": "(flabby:1.2), soft, (no veins:1.3), relaxed, weak, no definition",
  "Realistic Depth of Field": "flat focus, (all-in-focus:1.3), sharp background, deep focus, fake blur",
  "Chromatic Aberration (Natural)": "(clean digital edges:1.3), perfect focus, no fringing, flat",
  "Lens Grain & Texture": "(smooth:1.3), plastic, noise-free, digital, clean, unreal engine",
  "Anamorphic Distortion": "straight edges, (vertical:1.2), square, undistorted",
  "Accurate Motion Blur": "(static:1.3), frozen, sharp motion, no streaks, still",
  "Vanishing Point Accuracy": "(warped perspective:1.3), fish-eye, curved lines, architectural sagging, unstable",
  "Scale & Proportional Consistency": "(weird scale:1.3), tiny characters, massive objects, distorted volume, wrong depth",
  "Architectural Alignment": "(crooked:1.3), tilted, sagging, leaning walls, wobbly structures, bad construction",
  "Geometric Rigidity": "(wobbly edges:1.3), organic curves on machines, rounded corners, soft edges, hallucinated lines",
  "Refractive Material Physics": "(flat glass:1.3), no refraction, opaque, solid, no caustics, no distortion",
  "Specular Highlight Consistency": "(ghost lights:1.3), contradictory shadows, floating highlights, matte",
  "Material-Specific Friction": "(smooth:1.3), uniform texture, plastic, flat, no roughness, oily",
  "Fresnel Effect": "flat reflections, (no sheen:1.3), uniform reflectivity, matte",
  "Weathering & Surface Wear": "(pristine:1.3), clean, brand new, high-gloss, no scratches, perfect",
  "Global Illumination Logic": "(isolated glow:1.3), inconsistent light, contradictory shadows, dark spots",
  "Shadow Integrity & Penumbra": "(detached shadows:1.3), floating shadows, sharp edges, no ambient occlusion",
  "Accurate Light Fall-off": "(infinite light:1.3), uniform brightness, flat lighting, no decay",
  "Consistent Specular Logic": "(contradictory light:1.3), extra reflections, messy highlights, random light",
  "Atmospheric Light Interaction": "clear air, (no scattering:1.2), cold light, inconsistent temperature",
  "Anti-Hallucination Structure": "(floating objects:1.4), repeating patterns, (AI artifacts:1.3), incoherent logic",
  "High-Fidelity Edge Definition": "(pixel smearing:1.3), ghosting, blurry borders, halos, artifacts",
  "Neural Noise Suppression": "(checkerboard:1.3), digital noise, grain, messy gradients, artifacts",
  "Temporal & Spatial Stability": "localized blur, (flicker:1.2), uneven quality, over-sharpened spots",
  "Stable Micro-Detail Rendering": "hallucinated pores, (weird irises:1.3), bad hair, messy texture"
}